multisom/SOM.py
multisom/__init__.py
multisom/core.py
multisom/main.py
multisom/main_parallel.py
multisom-0.1.5.dist-info/licenses/LICENSE
multisom-0.1.5.dist-info/METADATA
multisom-0.1.5.dist-info/WHEEL
multisom-0.1.5.dist-info/top_level.txt
multisom-0.1.5.dist-info/RECORD
